libname/__init__.py
libname/converter.py
vanta_yc-0.0.2.dist-info/METADATA
vanta_yc-0.0.2.dist-info/WHEEL
vanta_yc-0.0.2.dist-info/top_level.txt
vanta_yc-0.0.2.dist-info/RECORD
