Metadata-Version: 2.1
Name: vanta-yc
Version: 0.0.2
Summary: Log to table converter package
Home-page: UNKNOWN
Author: YC
Author-email: <yatipa.c@vanta-capital.com>
License: UNKNOWN
Keywords: python,log,table,lob,mbp,onItch
Platform: UNKNOWN
Classifier: Development Status :: 1 - Planning
Classifier: Intended Audience :: Developers
Classifier: Programming Language :: Python :: 3
Classifier: Operating System :: Unix
Classifier: Operating System :: MacOS :: MacOS X
Classifier: Operating System :: Microsoft :: Windows
Requires-Dist: datetime
Requires-Dist: decimal
Requires-Dist: pandas
Requires-Dist: re
